Workbook

Sheet README
B2: HELIOS CONSUMER GmbH · FP&A Sample Model
B3: Illustrative portfolio project. Prepared by Prajit Jawahar
B5: Model | C5: 02: 12-Month Rolling Cash Flow Forecast (FY2025)
B6: Purpose | C6: Turn the operating plan into a month-by-month cash forecast: model collections and supplier payments with realistic timing lags, project the closing cash balance, and test it against a minimum-cash loan covenant.
B7: Techniques shown | C7: Driver-based direct cash forecast · receivables & payables timing lags · rolling opening/closing balance · covenant headroom test with status flag · chart.
B8: How to use | C8: Edit the blue assumptions on the 'Assumptions' tab (collection split, cost drivers, capex and tax timing), and the whole 12-month forecast and covenant test recompute.
B9: Currency / units | C9: All figures in EUR thousands (€000) unless stated.
B10: Data | C10: Sample / illustrative figures for a fictional company. Not real financials.
B12: Colour key
B13: Blue text | C13: Hard-coded input / assumption you can change
B14: Black text | C14: Formula, recalculates automatically
B15: Green text | C15: Links to another sheet
B16: Yellow fill | C16: Cells intended for you to fill in

Sheet Assumptions
B2: Cash Flow Assumptions
B3: All figures €000 unless shown as %. Blue = input you can change.
B5: Opening cash balance (Jan) | C5: 3000
B6: Collections, % in month of sale | C6: 0.45
B7: Collections, % in following month | C7: 0.55
B8: COGS as % of revenue | C8: 0.608
B9: Payroll per month | C9: 700
B10: Other operating expenses per month | C10: 396
B11: Minimum cash covenant | C11: 2000
B12: Opening receivables (collected in Jan) | C12: 2400
B13: Opening payables (paid in Jan) | C13: 1600
B15: Monthly drivers (€000)
B16: Driver | C16: Jan | D16: Feb | E16: Mar | F16: Apr | G16: May | H16: Jun | I16: Jul | J16: Aug | K16: Sep | L16: Oct | M16: Nov | N16: Dec
B17: Net revenue | C17: 3300 | D17: 3450 | E17: 3900 | F17: 3780 | G17: 3960 | H17: 3900 | I17: 3700 | J17: 3540 | K17: 4250 | L17: 4480 | M17: 4950 | N17: 6290
B18: Capital expenditure | C18: 0 | D18: 0 | E18: 400 | F18: 0 | G18: 0 | H18: 0 | I18: 0 | J18: 0 | K18: 600 | L18: 0 | M18: 0 | N18: 0
B19: Tax payments | C19: 0 | D19: 0 | E19: 350 | F19: 0 | G19: 0 | H19: 350 | I19: 0 | J19: 0 | K19: 350 | L19: 0 | M19: 0 | N19: 350
B21: Revenue drives collections; COGS (as % of revenue) drives supplier payments one month later.
B22: Timing: 45% of a month's sales are collected that month, 55% the next. Suppliers are paid the month after the cost is incurred.

Sheet Cash Flow
B2: FY2025 Direct Cash Flow Forecast
B3: EUR thousands (€000). Green = linked from Assumptions. Rolling monthly balance with covenant test.
B5: €000 | C5: Jan | D5: Feb | E5: Mar | F5: Apr | G5: May | H5: Jun | I5: Jul | J5: Aug | K5: Sep | L5: Oct | M5: Nov | N5: Dec
B6: Net revenue (memo) | C6: =Assumptions!C17 | D6: =Assumptions!D17 | E6: =Assumptions!E17 | F6: =Assumptions!F17 | G6: =Assumptions!G17 | H6: =Assumptions!H17 | I6: =Assumptions!I17 | J6: =Assumptions!J17 | ... N6: =Assumptions!N17
B7: CASH INFLOWS
B8: Collections from customers | C8: =Assumptions!$C$6*C6+Assumptions!$C$12 | D8: =Assumptions!$C$6*D6+Assumptions!$C$7*C6 | E8: =Assumptions!$C$6*E6+Assumptions!$C$7*D6 | F8: =Assumptions!$C$6*F6+Assumptions!$C$7*E6 | G8: =Assumptions!$C$6*G6+Assumptions!$C$7*F6 | H8: =Assumptions!$C$6*H6+Assumptions!$C$7*G6 | I8: =Assumptions!$C$6*I6+Assumptions!$C$7*H6 | J8: =Assumptions!$C$6*J6+Assumptions!$C$7*I6 | K8: =Assumptions!$C$6*K6+Assumptions!$C$7*J6 | ... N8: =Assumptions!$C$6*N6+Assumptions!$C$7*M6
B9: Other inflows | C9: 0 | D9: 0 | E9: 0 | F9: 0 | G9: 0 | H9: 0 | I9: 0 | J9: 0 | K9: 0 | L9: 0 | M9: 0 | N9: 0
B10: Total cash inflows | C10: =C8+C9 | D10: =D8+D9 | E10: =E8+E9 | F10: =F8+F9 | G10: =G8+G9 | H10: =H8+H9 | I10: =I8+I9 | J10: =J8+J9 | ... N10: =N8+N9
B11: CASH OUTFLOWS
B12: Supplier payments (COGS, 1-mo lag) | C12: =Assumptions!$C$13 | D12: =Assumptions!$C$8*C6 | E12: =Assumptions!$C$8*D6 | F12: =Assumptions!$C$8*E6 | G12: =Assumptions!$C$8*F6 | H12: =Assumptions!$C$8*G6 | I12: =Assumptions!$C$8*H6 | J12: =Assumptions!$C$8*I6 | K12: =Assumptions!$C$8*J6 | ... N12: =Assumptions!$C$8*M6
B13: Payroll | C13: =Assumptions!$C$9 | D13: =Assumptions!$C$9 | E13: =Assumptions!$C$9 | F13: =Assumptions!$C$9 | G13: =Assumptions!$C$9 | H13: =Assumptions!$C$9 | I13: =Assumptions!$C$9 | J13: =Assumptions!$C$9 | ... N13: =Assumptions!$C$9
B14: Other operating expenses | C14: =Assumptions!$C$10 | D14: =Assumptions!$C$10 | E14: =Assumptions!$C$10 | F14: =Assumptions!$C$10 | G14: =Assumptions!$C$10 | H14: =Assumptions!$C$10 | I14: =Assumptions!$C$10 | J14: =Assumptions!$C$10 | ... N14: =Assumptions!$C$10
B15: Capital expenditure | C15: =Assumptions!C18 | D15: =Assumptions!D18 | E15: =Assumptions!E18 | F15: =Assumptions!F18 | G15: =Assumptions!G18 | H15: =Assumptions!H18 | I15: =Assumptions!I18 | J15: =Assumptions!J18 | ... N15: =Assumptions!N18
B16: Tax payments | C16: =Assumptions!C19 | D16: =Assumptions!D19 | E16: =Assumptions!E19 | F16: =Assumptions!F19 | G16: =Assumptions!G19 | H16: =Assumptions!H19 | I16: =Assumptions!I19 | J16: =Assumptions!J19 | ... N16: =Assumptions!N19
B17: Total cash outflows | C17: =SUM(C12:C16) | D17: =SUM(D12:D16) | E17: =SUM(E12:E16) | F17: =SUM(F12:F16) | G17: =SUM(G12:G16) | H17: =SUM(H12:H16) | I17: =SUM(I12:I16) | J17: =SUM(J12:J16) | ... N17: =SUM(N12:N16)
B18: Net cash flow | C18: =C10-C17 | D18: =D10-D17 | E18: =E10-E17 | F18: =F10-F17 | G18: =G10-G17 | H18: =H10-H17 | I18: =I10-I17 | J18: =J10-J17 | ... N18: =N10-N17
B20: Opening cash | C20: =Assumptions!$C$5 | D20: =C21 | E20: =D21 | F20: =E21 | G20: =F21 | H20: =G21 | I20: =H21 | J20: =I21 | K20: =J21 | ... N20: =M21
B21: Closing cash | C21: =C20+C18 | D21: =D20+D18 | E21: =E20+E18 | F21: =F20+F18 | G21: =G20+G18 | H21: =H20+H18 | I21: =I20+I18 | J21: =J20+J18 | ... N21: =N20+N18
B22: Minimum cash covenant | C22: =Assumptions!$C$11 | D22: =Assumptions!$C$11 | E22: =Assumptions!$C$11 | F22: =Assumptions!$C$11 | G22: =Assumptions!$C$11 | H22: =Assumptions!$C$11 | I22: =Assumptions!$C$11 | J22: =Assumptions!$C$11 | ... N22: =Assumptions!$C$11
B23: Liquidity headroom | C23: =C21-C22 | D23: =D21-D22 | E23: =E21-E22 | F23: =F21-F22 | G23: =G21-G22 | H23: =H21-H22 | I23: =I21-I22 | J23: =J21-J22 | ... N23: =N21-N22
B24: Covenant status | C24: =IF(C21<C22,"BREACH","OK") | D24: =IF(D21<D22,"BREACH","OK") | E24: =IF(E21<E22,"BREACH","OK") | F24: =IF(F21<F22,"BREACH","OK") | G24: =IF(G21<G22,"BREACH","OK") | H24: =IF(H21<H22,"BREACH","OK") | I24: =IF(I21<I22,"BREACH","OK") | J24: =IF(J21<J22,"BREACH","OK") | ... N24: =IF(N21<N22,"BREACH","OK")
B42: Key insights (auto-generated)
B43: ="Cash builds from €"&TEXT(C20,"#,##0")&"k to €"&TEXT(N21,"#,##0")&"k over the year, generating €"&TEXT(N21-C20,"#,##0")&"k of net cash."
B44: ="The tightest month is when headroom is lowest, so watch Q1, when fixed costs and the March tax and capex outflow land before Q4 collections arrive."
B45: ="Every month clears the €"&TEXT(C22,"#,##0")&"k covenant; the smallest buffer is the value to manage with supplier terms or a revolving facility."
