Workbook

Sheet README
B2: HELIOS CONSUMER GmbH · Sample Model
B3: Illustrative portfolio project. Prepared by Prajit Jawahar
B5: Model | C5: 07: DCF & Comparable Company Valuation
B6: Purpose | C6: Value Helios Consumer GmbH two ways: an intrinsic discounted-cash-flow model and a market-based trading-comparables analysis, then triangulate to a share-price range.
B7: Techniques shown | C7: Unlevered FCF projection · WACC from CAPM · Gordon-growth terminal value · enterprise-to-equity bridge · trading comps (EV/EBITDA, P/E) · valuation range.
B8: How to use | C8: Change the blue drivers on 'Assumptions' (WACC inputs, growth, margins) or the peer multiples on 'Comps'; the DCF, comps and summary range all update.
B9: Currency / units | C9: See each sheet header for units.
B10: Data | C10: Sample / illustrative figures for a fictional company. Not real financials.
B12: Colour key
B13: Blue text | C13: Hard-coded input / assumption you can change
B14: Black text | C14: Formula, recalculates automatically
B15: Green text | C15: Links to another sheet
B16: Yellow fill | C16: Cells intended for you to fill in

Sheet Assumptions
B2: Valuation Assumptions
B3: €000 unless shown as %. Blue = input.
B5: Cost of capital (WACC)
B6: Risk-free rate | C6: 0.03
B7: Equity risk premium | C7: 0.06
B8: Beta | C8: 1.2
B9: Cost of equity | C9: =$C$6+$C$8*$C$7
B10: Pre-tax cost of debt | C10: 0.05
B11: Tax rate | C11: 0.3
B12: After-tax cost of debt | C12: =$C$10*(1-$C$11)
B13: Equity weight | C13: 0.65
B14: Debt weight | C14: 0.35
B15: WACC | C15: =$C$13*$C$9+$C$14*$C$12
B17: Operating & valuation drivers
B18: Base revenue, FY2025 | C18: 49500
B19: Prior-year revenue, FY2024 | C19: 45000
B20: EBIT margin | C20: 0.1
B21: D&A (% of revenue) | C21: 0.024
B22: Capex (% of revenue) | C22: 0.03
B23: Net working capital (days) | C23: 47
B24: Terminal growth rate | C24: 0.02
B25: Net debt | C25: 1558
B26: Shares outstanding (000s) | C26: 3000
B28: Revenue growth by year
B29: Revenue growth, FY2026 | C29: 0.07
B30: Revenue growth, FY2027 | C30: 0.06
B31: Revenue growth, FY2028 | C31: 0.05
B32: Revenue growth, FY2029 | C32: 0.04

Sheet DCF
B2: Discounted Cash Flow — Unlevered FCF
B3: €000. Green = linked from Assumptions.
B5: €000 | C5: FY2025 | D5: FY2026 | E5: FY2027 | F5: FY2028 | G5: FY2029
B6: Period (t) | C6: 1 | D6: 2 | E6: 3 | F6: 4 | G6: 5
B7: Revenue | C7: =Assumptions!$C$18 | D7: =C7*(1+Assumptions!$C$29) | E7: =D7*(1+Assumptions!$C$30) | F7: =E7*(1+Assumptions!$C$31) | G7: =F7*(1+Assumptions!$C$32)
B8: EBIT | C8: =C7*Assumptions!$C$20 | D8: =D7*Assumptions!$C$20 | E8: =E7*Assumptions!$C$20 | F8: =F7*Assumptions!$C$20 | G8: =G7*Assumptions!$C$20
B9: NOPAT (EBIT x (1-tax)) | C9: =C8*(1-Assumptions!$C$11) | D9: =D8*(1-Assumptions!$C$11) | E9: =E8*(1-Assumptions!$C$11) | F9: =F8*(1-Assumptions!$C$11) | G9: =G8*(1-Assumptions!$C$11)
B10: add: D&A | C10: =C7*Assumptions!$C$21 | D10: =D7*Assumptions!$C$21 | E10: =E7*Assumptions!$C$21 | F10: =F7*Assumptions!$C$21 | G10: =G7*Assumptions!$C$21
B11: less: Capex | C11: =-C7*Assumptions!$C$22 | D11: =-D7*Assumptions!$C$22 | E11: =-E7*Assumptions!$C$22 | F11: =-F7*Assumptions!$C$22 | G11: =-G7*Assumptions!$C$22
B12: less: change in NWC | C12: =-(C7-Assumptions!$C$19)*Assumptions!$C$23/365 | D12: =-(D7-C7)*Assumptions!$C$23/365 | E12: =-(E7-D7)*Assumptions!$C$23/365 | F12: =-(F7-E7)*Assumptions!$C$23/365 | G12: =-(G7-F7)*Assumptions!$C$23/365
B13: Unlevered FCF | C13: =C9+C10+C11+C12 | D13: =D9+D10+D11+D12 | E13: =E9+E10+E11+E12 | F13: =F9+F10+F11+F12 | G13: =G9+G10+G11+G12
B14: Discount factor | C14: =1/POWER(1+Assumptions!$C$15,C6) | D14: =1/POWER(1+Assumptions!$C$15,D6) | E14: =1/POWER(1+Assumptions!$C$15,E6) | F14: =1/POWER(1+Assumptions!$C$15,F6) | G14: =1/POWER(1+Assumptions!$C$15,G6)
B15: PV of FCF | C15: =C13*C14 | D15: =D13*D14 | E15: =E13*E14 | F15: =F13*F14 | G15: =G13*G14
B17: Sum of PV of FCF (FY2025-FY2029) | C17: =SUM(C15:G15)
B18: Terminal value (Gordon growth) | C18: =G13*(1+Assumptions!$C$24)/(Assumptions!$C$15-Assumptions!$C$24)
B19: PV of terminal value | C19: =C18*G14
B20: Enterprise value | C20: =C17+C19
B21: less: Net debt | C21: =-Assumptions!$C$25
B22: Equity value | C22: =C20+C21
B23: DCF value per share (EUR) | C23: =C22/Assumptions!$C$26

Sheet Comps
B2: Trading Comparables
B3: Peer multiples applied to Helios. Green = linked from DCF.
B5: Peer company | C5: EV / EBITDA | D5: P / E
B6: Nordwind Appliances | C6: 9.2 | D6: 15.5
B7: Rheingold Electronics | C7: 10.4 | D7: 18
B8: Alpina Home | C8: 8.6 | D8: 14.2
B9: Vega Consumer | C9: 11.1 | D9: 19.5
B10: Meridian Devices | C10: 9.8 | D10: 16.8
B11: Median | C11: =MEDIAN(C6:C10) | D11: =MEDIAN(D6:D10)
B12: Mean | C12: =AVERAGE(C6:C10) | D12: =AVERAGE(D6:D10)
B14: Implied valuation of Helios (€000)
B15: Helios EBITDA, FY2025 | C15: =DCF!C8+DCF!C10
B16: Helios net income, FY2025 | C16: =DCF!C9-Assumptions!$C$10*Assumptions!$C$25*(1-Assumptions!$C$11)
B17: Implied EV (median EV/EBITDA) | C17: =C11*C15
B18: Implied equity (EV/EBITDA) | C18: =C17-Assumptions!$C$25
B19: Value/share, EV/EBITDA (EUR) | C19: =C18/Assumptions!$C$26
B20: Implied equity (median P/E) | C20: =D11*C16
B21: Value/share, P/E (EUR) | C21: =C20/Assumptions!$C$26

Sheet Summary
B2: Valuation Summary — Value per Share (EUR)
B3: Triangulation across methods.
B5: Method | C5: Value / share
B6: DCF (intrinsic) | C6: =DCF!C23
B7: Comps — EV/EBITDA | C7: =Comps!C19
B8: Comps — P/E | C8: =Comps!C21
B9: Low | C9: =MIN(C6:C8)
B10: Midpoint | C10: =MEDIAN(C6:C8)
B11: High | C11: =MAX(C6:C8)
B14: Key insight (auto-generated)
B15: ="Triangulated value of about €"&TEXT(C8,"0.00")&" per share (range €"&TEXT(C6,"0.00")&" to €"&TEXT(C11,"0.00")&"), where DCF and market multiples broadly agree."
