Workbook

Sheet README
B2: HELIOS CONSUMER GmbH · Sample Model
B3: Illustrative portfolio project. Prepared by Prajit Jawahar
B5: Model | C5: 23: Long-Range Plan (7-Year Integrated Model)
B6: Purpose | C6: A seven-year integrated plan for Helios that flexes across strategic options (organic base, accelerated investment, M&A-led), builds unlevered free cash flow and a DCF value, and compares the long-term value each strategy creates.
B7: Techniques shown | C7: 7-year integrated P&L to cash flow · CHOOSE strategic-scenario switch · unlevered FCF and cumulative cash · DCF enterprise value · strategic-options value comparison.
B8: How to use | C8: Set the blue scenario switch (1 Base / 2 Accelerated / 3 M&A) and drivers on 'Assumptions'; the whole plan, DCF value and options table recompute.
B9: Currency / units | C9: See each sheet header for units.
B10: Data | C10: Sample / illustrative figures for a fictional company. Not real financials.
B12: Blue text | C12: Hard-coded input / assumption you can change
B13: Black text | C13: Formula, recalculates automatically
B14: Green text | C14: Links to another sheet
B15: Yellow fill | C15: Cells intended for you to fill in

Sheet Assumptions
B2: Long-Range Plan — Assumptions
B3: €000 unless %. Blue = input.
B5: Corporate & valuation
B6: Prior-year revenue, FY2024 | C6: 45000
B7: WACC | C7: 0.08
B8: Terminal growth | C8: 0.02
B9: Exit EV/EBITDA multiple | C9: 8.5
B10: Tax rate | C10: 0.3
B11: D&A (% of revenue) | C11: 0.024
B12: Net working capital (days) | C12: 47
B13: Net debt | C13: 1558
B14: Shares outstanding (000s) | C14: 3000
B16: Scenario switch (1=Base, 2=Accelerated, 3=M&A) | C16: 1
B18: Strategic scenarios
B19: Scenario | C19: Revenue CAGR | D19: EBITDA margin | E19: Capex % rev
B20: Base (organic) | C20: 0.06 | D20: 0.125 | E20: 0.03
B21: Accelerated investment | C21: 0.1 | D21: 0.13 | E21: 0.045
B22: M&A-led | C22: 0.14 | D22: 0.125 | E22: 0.04

Sheet Long-Range Plan
B2: Helios Consumer GmbH — 7-Year Long-Range Plan
B3: €000. Green = linked from Assumptions. Driven by the selected strategic scenario.
B5: Selected revenue CAGR | C5: =CHOOSE(Assumptions!$C$16,Assumptions!$C$20,Assumptions!$C$21,Assumptions!$C$22)
B6: Selected EBITDA margin | C6: =CHOOSE(Assumptions!$C$16,Assumptions!$D$20,Assumptions!$D$21,Assumptions!$D$22)
B7: Selected capex % of revenue | C7: =CHOOSE(Assumptions!$C$16,Assumptions!$E$20,Assumptions!$E$21,Assumptions!$E$22)
B9: €000 | C9: FY2025 | D9: FY2026 | E9: FY2027 | F9: FY2028 | G9: FY2029 | H9: FY2030 | I9: FY2031
B10: Period (t) | C10: 1 | D10: 2 | E10: 3 | F10: 4 | G10: 5 | H10: 6 | I10: 7
B11: Revenue | C11: =Assumptions!$C$6*(1+$C$5) | D11: =C11*(1+$C$5) | E11: =D11*(1+$C$5) | F11: =E11*(1+$C$5) | G11: =F11*(1+$C$5) | H11: =G11*(1+$C$5) | I11: =H11*(1+$C$5)
B12: EBITDA | C12: =C11*$C$6 | D12: =D11*$C$6 | E12: =E11*$C$6 | F12: =F11*$C$6 | G12: =G11*$C$6 | H12: =H11*$C$6 | I12: =I11*$C$6
B13: EBITDA margin | C13: =C12/C11 | D13: =D12/D11 | E13: =E12/E11 | F13: =F12/F11 | G13: =G12/G11 | H13: =H12/H11 | I13: =I12/I11
B14: less: D&A | C14: =-C11*Assumptions!$C$11 | D14: =-D11*Assumptions!$C$11 | E14: =-E11*Assumptions!$C$11 | F14: =-F11*Assumptions!$C$11 | G14: =-G11*Assumptions!$C$11 | H14: =-H11*Assumptions!$C$11 | I14: =-I11*Assumptions!$C$11
B15: EBIT | C15: =C12+C14 | D15: =D12+D14 | E15: =E12+E14 | F15: =F12+F14 | G15: =G12+G14 | H15: =H12+H14 | I15: =I12+I14
B16: NOPAT | C16: =C15*(1-Assumptions!$C$10) | D16: =D15*(1-Assumptions!$C$10) | E16: =E15*(1-Assumptions!$C$10) | F16: =F15*(1-Assumptions!$C$10) | G16: =G15*(1-Assumptions!$C$10) | H16: =H15*(1-Assumptions!$C$10) | I16: =I15*(1-Assumptions!$C$10)
B17: add: D&A | C17: =-C14 | D17: =-D14 | E17: =-E14 | F17: =-F14 | G17: =-G14 | H17: =-H14 | I17: =-I14
B18: less: capex | C18: =-C11*$C$7 | D18: =-D11*$C$7 | E18: =-E11*$C$7 | F18: =-F11*$C$7 | G18: =-G11*$C$7 | H18: =-H11*$C$7 | I18: =-I11*$C$7
B19: less: change in NWC | C19: =-(C11-Assumptions!$C$6)*Assumptions!$C$12/365 | D19: =-(D11-C11)*Assumptions!$C$12/365 | E19: =-(E11-D11)*Assumptions!$C$12/365 | F19: =-(F11-E11)*Assumptions!$C$12/365 | G19: =-(G11-F11)*Assumptions!$C$12/365 | H19: =-(H11-G11)*Assumptions!$C$12/365 | I19: =-(I11-H11)*Assumptions!$C$12/365
B20: Unlevered FCF | C20: =C16+C17+C18+C19 | D20: =D16+D17+D18+D19 | E20: =E16+E17+E18+E19 | F20: =F16+F17+F18+F19 | G20: =G16+G17+G18+G19 | H20: =H16+H17+H18+H19 | I20: =I16+I17+I18+I19
B21: Cumulative FCF | C21: =C20 | D21: =C21+D20 | E21: =D21+E20 | F21: =E21+F20 | G21: =F21+G20 | H21: =G21+H20 | I21: =H21+I20
B22: Discount factor | C22: =1/POWER(1+Assumptions!$C$7,C10) | D22: =1/POWER(1+Assumptions!$C$7,D10) | E22: =1/POWER(1+Assumptions!$C$7,E10) | F22: =1/POWER(1+Assumptions!$C$7,F10) | G22: =1/POWER(1+Assumptions!$C$7,G10) | H22: =1/POWER(1+Assumptions!$C$7,H10) | I22: =1/POWER(1+Assumptions!$C$7,I10)
B23: PV of FCF | C23: =C20*C22 | D23: =D20*D22 | E23: =E20*E22 | F23: =F20*F22 | G23: =G20*G22 | H23: =H20*H22 | I23: =I20*I22
B25: Sum of PV of FCF | C25: =SUM(C23:I23)
B26: Terminal value (Gordon) | C26: =I20*(1+Assumptions!$C$8)/(Assumptions!$C$7-Assumptions!$C$8)
B27: PV of terminal value | C27: =C26*I22
B28: Enterprise value (DCF) | C28: =C25+C27
B29: Equity value | C29: =C28-Assumptions!$C$13
B30: Value per share (EUR) | C30: =C29/Assumptions!$C$14
B32: Strategic options — value comparison (terminal exit value)
B33: Strategy | C33: Rev CAGR | D33: FY2031 revenue | E33: FY2031 EBITDA | F33: Terminal EV | G33: Value vs Base
B34: Base (organic) | C34: =Assumptions!$C$20 | D34: =Assumptions!$C$6*POWER(1+Assumptions!$C$20,7) | E34: =D34*Assumptions!$D$20 | F34: =E34*Assumptions!$C$9 | G34: =F34-$F$34
B35: Accelerated investment | C35: =Assumptions!$C$21 | D35: =Assumptions!$C$6*POWER(1+Assumptions!$C$21,7) | E35: =D35*Assumptions!$D$21 | F35: =E35*Assumptions!$C$9 | G35: =F35-$F$34
B36: M&A-led | C36: =Assumptions!$C$22 | D36: =Assumptions!$C$6*POWER(1+Assumptions!$C$22,7) | E36: =D36*Assumptions!$D$22 | F36: =E36*Assumptions!$C$9 | G36: =F36-$F$34
B38: Key insights (auto-generated)
B39: ="Selected strategy plans revenue to €"&TEXT(I11,"#,##0")&"k by FY2031 and a DCF enterprise value of €"&TEXT(C28,"#,##0")&"k today."
B40: ="Across strategic options, the M&A-led path builds the most terminal value but the accelerated-investment path improves value with less integration risk."
B41: ="The integrated model links growth, margin, capex and working capital, so each strategic lever flows through to cash and long-term value."
