Workbook

Sheet Inputs
A1: Deutsche Börse AG (DB1) — DCF Inputs | all € million unless stated
A3: FY2025 ACTUALS (preliminary results, 11 Feb 2026)
A4: Net revenue w/o treasury result | B4: 5189 | C4: Company release p.3
A5: Treasury result (banking & similar) | B5: 837 | C5: Company release p.3 (2024: 1,050)
A6: Net revenue, total | B6: 6026 | C6: sum of the two rows above
A7: Operating costs | B7: 2534 | C7: Company release p.3
A8: EBITDA, total | B8: 3512 | C8: Company release p.3
A9: EBITDA w/o treasury result | B9: 2675 | C9: Company release p.3
A10: Depreciation, amortisation & impairment | B10: 502 | C10: Company release p.3
A11: EBIT | B11: 3010 | C11: Company release p.3
A12: Earnings before tax | B12: 2857 | C12: Company release p.3
A13: Income tax & other tax | B13: 753 | C13: Company release p.3
A14: Effective tax rate | B14: =B13/B12 | C14: derived
A15: Net profit attrib. to DB1 shareholders | B15: 1995 | C15: Company release p.3
A16: Net profit attrib. to minorities | B16: 109 | C16: Company release p.3
A17: FY2026 COMPANY GUIDANCE (CMD 10 Dec 2025)
A18: Net revenue w/o treasury, 2026E | B18: 5700 | C18: Company release p.2
A19: EBITDA w/o treasury, 2026E | B19: 3100 | C19: Company release p.2
A20: Treasury result, 2026E | B20: 700 | C20: Company release p.2 ('around €0.7bn')
A21: MARKET DATA (stockanalysis.com, 6 Oct 2026)
A22: Share price, € | B22: 293.7 | C22: ETR:DB1
A23: Shares outstanding, million | B23: 180.29 | C23: post-buyback count
A24: Net debt | B24: 4410 | C24: total debt 6,190 less cash 1,780
A25: Total debt (for WACC weights) | B25: 6190 | C25: stockanalysis.com
A26: ANALYST ASSUMPTIONS (mine — challenge these)
A27: Risk-free rate (10Y Bund) | B27: 0.026 | C27: [verify on posting day]
A28: Equity risk premium | B28: 0.055 | C28: Damodaran, mature market
A29: Beta (levered, judgement) | B29: 0.7 | C29: 5Y raw beta 0.30 looks too low; peer-informed
A30: Pre-tax cost of debt | B30: 0.035 | C30: recent DB1 bond yields, approx.
A31: Terminal growth g | B31: 0.02 | C31: ≈ long-run eurozone inflation
A32: Rev w/o treasury growth 2027-2030 | B32: 8% / 7% / 6% / 5% | C32: taper from 9.8% guidance year
A33: EBITDA-xT margin path 2026-2030 | B33: 54.4% → 56.0% | C33: +0.4pt/yr operating leverage, capped
A34: Treasury result 2027-2030 | B34: 700 | C34: held flat at guidance level
A35: D&A as % of rev w/o treasury | B35: =B10/B4 | C35: FY2025 ratio held
A36: Capex as % of D&A | B36: 1.1 | C36: intangible-heavy reinvestment
A37: Change in working capital | B37: 0 | C37: fee business; banking WC excluded — see note
A38: Minority interest valuation multiple | B38: 20 | C38: × minority net profit (book value n/a in prelim.)
A40: Note: Clearstream's client cash balances make DB1 a part-bank. Classic working-capital forecasting is meaningless here; the banking book shows up through the treasury result line instead. This model values FCFF = EBITDA (incl. treasury result, treated as operating) − cash tax on EBIT − capex.

Sheet DCF
A1: DCF — FCFF, 2026E–2030E | € million
A3: Year | B3: 2026E | C3: 2027E | D3: 2028E | E3: 2029E | F3: 2030E
A4: Rev w/o treasury growth | B4: =Inputs!$B$18/Inputs!$B$4-1 | C4: 0.08 | D4: 0.07 | E4: 0.06 | F4: 0.05
A5: Net revenue w/o treasury | B5: =Inputs!$B$18 | C5: =B5*(1+C4) | D5: =C5*(1+D4) | E5: =D5*(1+E4) | F5: =E5*(1+F4)
A6: EBITDA-xT margin | B6: =Inputs!$B$19/Inputs!$B$18 | C6: =MIN(B6+0.004,0.56) | D6: =MIN(C6+0.004,0.56) | E6: =MIN(D6+0.004,0.56) | F6: =MIN(E6+0.004,0.56)
A7: EBITDA w/o treasury | B7: =B5*B6 | C7: =C5*C6 | D7: =D5*D6 | E7: =E5*E6 | F7: =F5*F6
A8: Treasury result | B8: =Inputs!$B$20 | C8: =Inputs!$B$34 | D8: =Inputs!$B$34 | E8: =Inputs!$B$34 | F8: =Inputs!$B$34
A9: EBITDA, total | B9: =B7+B8 | C9: =C7+C8 | D9: =D7+D8 | E9: =E7+E8 | F9: =F7+F8
A10: D&A | B10: =-B5*Inputs!$B$35 | C10: =-C5*Inputs!$B$35 | D10: =-D5*Inputs!$B$35 | E10: =-E5*Inputs!$B$35 | F10: =-F5*Inputs!$B$35
A11: EBIT | B11: =B9+B10 | C11: =C9+C10 | D11: =D9+D10 | E11: =E9+E10 | F11: =F9+F10
A12: Cash tax on EBIT | B12: =-B11*Inputs!$B$14 | C12: =-C11*Inputs!$B$14 | D12: =-D11*Inputs!$B$14 | E12: =-E11*Inputs!$B$14 | F12: =-F11*Inputs!$B$14
A13: Capex | B13: =B10*Inputs!$B$36 | C13: =C10*Inputs!$B$36 | D13: =D10*Inputs!$B$36 | E13: =E10*Inputs!$B$36 | F13: =F10*Inputs!$B$36
A14: Change in WC | B14: =Inputs!$B$37 | C14: =Inputs!$B$37 | D14: =Inputs!$B$37 | E14: =Inputs!$B$37 | F14: =Inputs!$B$37
A15: FCFF | B15: =B9+B12+B13+B14 | C15: =C9+C12+C13+C14 | D15: =D9+D12+D13+D14 | E15: =E9+E12+E13+E14 | F15: =F9+F12+F13+F14
A16: Discount factor | B16: =1/(1+$B$22)^1 | C16: =1/(1+$B$22)^2 | D16: =1/(1+$B$22)^3 | E16: =1/(1+$B$22)^4 | F16: =1/(1+$B$22)^5
A17: PV of FCFF | B17: =B15*B16 | C17: =C15*C16 | D17: =D15*D16 | E17: =E15*E16 | F17: =F15*F16
A19: WACC
A20: Cost of equity (CAPM) | B20: =Inputs!$B$27+Inputs!$B$29*Inputs!$B$28
A21: After-tax cost of debt | B21: =Inputs!$B$30*(1-Inputs!$B$14)
A22: WACC | B22: =(Inputs!$B$22*Inputs!$B$23/(Inputs!$B$22*Inputs!$B$23+Inputs!$B$25))*B20+(Inputs!$B$25/(Inputs!$B$22*Inputs!$B$23+Inputs!$B$25))*B21
A24: VALUATION BRIDGE
A25: Sum PV of FCFF 2026-2030 | B25: =SUM(B17:F17)
A26: Terminal value (Gordon, at 2030) | B26: =F15*(1+Inputs!$B$31)/($B$22-Inputs!$B$31)
A27: PV of terminal value | B27: =B26*F16
A28: Enterprise value | B28: =B25+B27
A29: Less: net debt | B29: =-Inputs!$B$24
A30: Less: minority interest (est.) | B30: =-Inputs!$B$16*Inputs!$B$38
A31: Equity value | B31: =B28+B29+B30
A32: Value per share, € | B32: =B31/Inputs!$B$23
A33: Share price (6 Oct 2026), € | B33: =Inputs!$B$22
A34: Upside / (downside) | B34: =B32/B33-1
A36: WHAT THE MARKET PRICE IMPLIES
A37: Market-implied enterprise value | B37: =Inputs!$B$22*Inputs!$B$23+Inputs!$B$24+Inputs!$B$16*Inputs!$B$38
A38: Required terminal value at 2030 | B38: =(B37-B25)/F16
A39: Implied perpetual growth g* | B39: =($B$22*B38-F15)/(B38+F15)

Sheet Sensitivity
A1: Value per share (€) — terminal growth × WACC
A3: g \ WACC | B3: 0.055 | C3: 0.0575 | D3: 0.06 | E3: 0.0625 | F3: 0.065
A4: 0.01 | B4: =((DCF!B15/(1+B$3)^1+DCF!C15/(1+B$3)^2+DCF!D15/(1+B$3)^3+DCF!E15/(1+B$3)^4+DCF!F15/(1+B$3)^5)+DCF!F15*(1+$A$4)/(B$3-$A$4)/(1+B$3)^5-Inputs!$B$24-Inputs!$B$16*Inputs!$B$38)/Inputs!$B$23 | C4: =((DCF!B15/(1+C$3)^1+DCF!C15/(1+C$3)^2+DCF!D15/(1+C$3)^3+DCF!E15/(1+C$3)^4+DCF!F15/(1+C$3)^5)+DCF!F15*(1+$A$4)/(C$3-$A$4)/(1+C$3)^5-Inputs!$B$24-Inputs!$B$16*Inputs!$B$38)/Inputs!$B$23 | D4: =((DCF!B15/(1+D$3)^1+DCF!C15/(1+D$3)^2+DCF!D15/(1+D$3)^3+DCF!E15/(1+D$3)^4+DCF!F15/(1+D$3)^5)+DCF!F15*(1+$A$4)/(D$3-$A$4)/(1+D$3)^5-Inputs!$B$24-Inputs!$B$16*Inputs!$B$38)/Inputs!$B$23 | E4: =((DCF!B15/(1+E$3)^1+DCF!C15/(1+E$3)^2+DCF!D15/(1+E$3)^3+DCF!E15/(1+E$3)^4+DCF!F15/(1+E$3)^5)+DCF!F15*(1+$A$4)/(E$3-$A$4)/(1+E$3)^5-Inputs!$B$24-Inputs!$B$16*Inputs!$B$38)/Inputs!$B$23 | F4: =((DCF!B15/(1+F$3)^1+DCF!C15/(1+F$3)^2+DCF!D15/(1+F$3)^3+DCF!E15/(1+F$3)^4+DCF!F15/(1+F$3)^5)+DCF!F15*(1+$A$4)/(F$3-$A$4)/(1+F$3)^5-Inputs!$B$24-Inputs!$B$16*Inputs!$B$38)/Inputs!$B$23
A5: 0.015 | B5: =((DCF!B15/(1+B$3)^1+DCF!C15/(1+B$3)^2+DCF!D15/(1+B$3)^3+DCF!E15/(1+B$3)^4+DCF!F15/(1+B$3)^5)+DCF!F15*(1+$A$5)/(B$3-$A$5)/(1+B$3)^5-Inputs!$B$24-Inputs!$B$16*Inputs!$B$38)/Inputs!$B$23 | C5: =((DCF!B15/(1+C$3)^1+DCF!C15/(1+C$3)^2+DCF!D15/(1+C$3)^3+DCF!E15/(1+C$3)^4+DCF!F15/(1+C$3)^5)+DCF!F15*(1+$A$5)/(C$3-$A$5)/(1+C$3)^5-Inputs!$B$24-Inputs!$B$16*Inputs!$B$38)/Inputs!$B$23 | D5: =((DCF!B15/(1+D$3)^1+DCF!C15/(1+D$3)^2+DCF!D15/(1+D$3)^3+DCF!E15/(1+D$3)^4+DCF!F15/(1+D$3)^5)+DCF!F15*(1+$A$5)/(D$3-$A$5)/(1+D$3)^5-Inputs!$B$24-Inputs!$B$16*Inputs!$B$38)/Inputs!$B$23 | E5: =((DCF!B15/(1+E$3)^1+DCF!C15/(1+E$3)^2+DCF!D15/(1+E$3)^3+DCF!E15/(1+E$3)^4+DCF!F15/(1+E$3)^5)+DCF!F15*(1+$A$5)/(E$3-$A$5)/(1+E$3)^5-Inputs!$B$24-Inputs!$B$16*Inputs!$B$38)/Inputs!$B$23 | F5: =((DCF!B15/(1+F$3)^1+DCF!C15/(1+F$3)^2+DCF!D15/(1+F$3)^3+DCF!E15/(1+F$3)^4+DCF!F15/(1+F$3)^5)+DCF!F15*(1+$A$5)/(F$3-$A$5)/(1+F$3)^5-Inputs!$B$24-Inputs!$B$16*Inputs!$B$38)/Inputs!$B$23
A6: 0.02 | B6: =((DCF!B15/(1+B$3)^1+DCF!C15/(1+B$3)^2+DCF!D15/(1+B$3)^3+DCF!E15/(1+B$3)^4+DCF!F15/(1+B$3)^5)+DCF!F15*(1+$A$6)/(B$3-$A$6)/(1+B$3)^5-Inputs!$B$24-Inputs!$B$16*Inputs!$B$38)/Inputs!$B$23 | C6: =((DCF!B15/(1+C$3)^1+DCF!C15/(1+C$3)^2+DCF!D15/(1+C$3)^3+DCF!E15/(1+C$3)^4+DCF!F15/(1+C$3)^5)+DCF!F15*(1+$A$6)/(C$3-$A$6)/(1+C$3)^5-Inputs!$B$24-Inputs!$B$16*Inputs!$B$38)/Inputs!$B$23 | D6: =((DCF!B15/(1+D$3)^1+DCF!C15/(1+D$3)^2+DCF!D15/(1+D$3)^3+DCF!E15/(1+D$3)^4+DCF!F15/(1+D$3)^5)+DCF!F15*(1+$A$6)/(D$3-$A$6)/(1+D$3)^5-Inputs!$B$24-Inputs!$B$16*Inputs!$B$38)/Inputs!$B$23 | E6: =((DCF!B15/(1+E$3)^1+DCF!C15/(1+E$3)^2+DCF!D15/(1+E$3)^3+DCF!E15/(1+E$3)^4+DCF!F15/(1+E$3)^5)+DCF!F15*(1+$A$6)/(E$3-$A$6)/(1+E$3)^5-Inputs!$B$24-Inputs!$B$16*Inputs!$B$38)/Inputs!$B$23 | F6: =((DCF!B15/(1+F$3)^1+DCF!C15/(1+F$3)^2+DCF!D15/(1+F$3)^3+DCF!E15/(1+F$3)^4+DCF!F15/(1+F$3)^5)+DCF!F15*(1+$A$6)/(F$3-$A$6)/(1+F$3)^5-Inputs!$B$24-Inputs!$B$16*Inputs!$B$38)/Inputs!$B$23
A7: 0.025 | B7: =((DCF!B15/(1+B$3)^1+DCF!C15/(1+B$3)^2+DCF!D15/(1+B$3)^3+DCF!E15/(1+B$3)^4+DCF!F15/(1+B$3)^5)+DCF!F15*(1+$A$7)/(B$3-$A$7)/(1+B$3)^5-Inputs!$B$24-Inputs!$B$16*Inputs!$B$38)/Inputs!$B$23 | C7: =((DCF!B15/(1+C$3)^1+DCF!C15/(1+C$3)^2+DCF!D15/(1+C$3)^3+DCF!E15/(1+C$3)^4+DCF!F15/(1+C$3)^5)+DCF!F15*(1+$A$7)/(C$3-$A$7)/(1+C$3)^5-Inputs!$B$24-Inputs!$B$16*Inputs!$B$38)/Inputs!$B$23 | D7: =((DCF!B15/(1+D$3)^1+DCF!C15/(1+D$3)^2+DCF!D15/(1+D$3)^3+DCF!E15/(1+D$3)^4+DCF!F15/(1+D$3)^5)+DCF!F15*(1+$A$7)/(D$3-$A$7)/(1+D$3)^5-Inputs!$B$24-Inputs!$B$16*Inputs!$B$38)/Inputs!$B$23 | E7: =((DCF!B15/(1+E$3)^1+DCF!C15/(1+E$3)^2+DCF!D15/(1+E$3)^3+DCF!E15/(1+E$3)^4+DCF!F15/(1+E$3)^5)+DCF!F15*(1+$A$7)/(E$3-$A$7)/(1+E$3)^5-Inputs!$B$24-Inputs!$B$16*Inputs!$B$38)/Inputs!$B$23 | F7: =((DCF!B15/(1+F$3)^1+DCF!C15/(1+F$3)^2+DCF!D15/(1+F$3)^3+DCF!E15/(1+F$3)^4+DCF!F15/(1+F$3)^5)+DCF!F15*(1+$A$7)/(F$3-$A$7)/(1+F$3)^5-Inputs!$B$24-Inputs!$B$16*Inputs!$B$38)/Inputs!$B$23
A8: 0.03 | B8: =((DCF!B15/(1+B$3)^1+DCF!C15/(1+B$3)^2+DCF!D15/(1+B$3)^3+DCF!E15/(1+B$3)^4+DCF!F15/(1+B$3)^5)+DCF!F15*(1+$A$8)/(B$3-$A$8)/(1+B$3)^5-Inputs!$B$24-Inputs!$B$16*Inputs!$B$38)/Inputs!$B$23 | C8: =((DCF!B15/(1+C$3)^1+DCF!C15/(1+C$3)^2+DCF!D15/(1+C$3)^3+DCF!E15/(1+C$3)^4+DCF!F15/(1+C$3)^5)+DCF!F15*(1+$A$8)/(C$3-$A$8)/(1+C$3)^5-Inputs!$B$24-Inputs!$B$16*Inputs!$B$38)/Inputs!$B$23 | D8: =((DCF!B15/(1+D$3)^1+DCF!C15/(1+D$3)^2+DCF!D15/(1+D$3)^3+DCF!E15/(1+D$3)^4+DCF!F15/(1+D$3)^5)+DCF!F15*(1+$A$8)/(D$3-$A$8)/(1+D$3)^5-Inputs!$B$24-Inputs!$B$16*Inputs!$B$38)/Inputs!$B$23 | E8: =((DCF!B15/(1+E$3)^1+DCF!C15/(1+E$3)^2+DCF!D15/(1+E$3)^3+DCF!E15/(1+E$3)^4+DCF!F15/(1+E$3)^5)+DCF!F15*(1+$A$8)/(E$3-$A$8)/(1+E$3)^5-Inputs!$B$24-Inputs!$B$16*Inputs!$B$38)/Inputs!$B$23 | F8: =((DCF!B15/(1+F$3)^1+DCF!C15/(1+F$3)^2+DCF!D15/(1+F$3)^3+DCF!E15/(1+F$3)^4+DCF!F15/(1+F$3)^5)+DCF!F15*(1+$A$8)/(F$3-$A$8)/(1+F$3)^5-Inputs!$B$24-Inputs!$B$16*Inputs!$B$38)/Inputs!$B$23
A10: Swing from ±0.5pt terminal growth (at 6.0% WACC):
A11: g = 1.5% vs base 2.0% | B11: =D5/D6-1
A12: g = 2.5% vs base 2.0% | B12: =D7/D6-1
A14: Sources: DB1 preliminary FY2025 results (11 Feb 2026); stockanalysis.com (6 Oct 2026). Model: Prajit Jawahar.
